bsh_file_validation/__init__.py
bsh_file_validation/bsh_validator.py
bsh_file_validation/bsh_validator_license_key.py
bsh_file_validation/f_attribute_retriever.py
bsh_file_validation/f_attribute_validator.py
bsh_file_validation/f_database_connect.py
bsh_file_validation/f_db_reader.py
bsh_file_validation/f_log_files.py
bsh_file_validation/f_logs.py
bsh_file_validation/f_retrive_listofattributes.py
bsh_file_validation/f_retrive_listoffiles.py
bsh_file_validation/f_utility_functions.py
bsh_file_validation/file_validation.py
bsh_file_validation/get_sparkutils.py
bsh_file_validation/test.py
dqf_validation/F_AttributeValidator2.py
dqf_validation/F_AttributeValidator4.py
dqf_validation/F_Dbconfigreader.py
dqf_validation/F_Dbreader.py
dqf_validation/F_Dbwriters.py
dqf_validation/F_Extract_channels.py
dqf_validation/F_Movefiles.py
dqf_validation/F_UtilityFunctions.py
dqf_validation/F_csvtxtreader.py
dqf_validation/F_databaseconnect.py
dqf_validation/F_datamasking.py
dqf_validation/F_dataunmasking.py
dqf_validation/F_delta_table_load.py
dqf_validation/F_delta_table_load_2.py
dqf_validation/F_filereader.py
dqf_validation/F_filereader2.py
dqf_validation/F_iot_schema.py
dqf_validation/F_iotdata_reader.py
dqf_validation/F_json_2reader.py
dqf_validation/F_jsonreader.py
dqf_validation/F_kafka_reader.py
dqf_validation/F_kafka_schema.py
dqf_validation/F_logs.py
dqf_validation/F_monit.py
dqf_validation/F_parquetreader.py
dqf_validation/F_stream_powerbi.py
dqf_validation/F_xmlreader.py
dqf_validation/NB_DEV_kafka analytics 172.py
dqf_validation/NB_DQF_Validator.py
dqf_validation/NB_stream_monitor.py
dqf_validation/NB_stream_to_powerbi.py
dqf_validation/NB_streaming analytics.py
dqf_validation/__init__.py
dqf_validation/encryption_nb_dqf_validation.py
dqf_validation/get_sparkutils.py
bsh_file_validation-0.0.21.dist-info/LICENSE.txt
bsh_file_validation-0.0.21.dist-info/METADATA
bsh_file_validation-0.0.21.dist-info/WHEEL
bsh_file_validation-0.0.21.dist-info/top_level.txt
bsh_file_validation-0.0.21.dist-info/RECORD
